{
  "plugins": {
    "Comment.nvim": {
      "rev": "e30b7f2008e52442154b66f7c519bfd2f1e32acb",
      "src": "https://github.com/numToStr/Comment.nvim"
    },
    "alpha-nvim": {
      "rev": "3979b01cb05734331c7873049001d3f2bb8477f4",
      "src": "https://github.com/goolord/alpha-nvim"
    },
    "auto-session": {
      "rev": "292492ab7af4bd8b9e37e28508bc8ce995722fd5",
      "src": "https://github.com/rmagatti/auto-session"
    },
    "cmp-buffer": {
      "rev": "b74fab3656eea9de20a9b8116afa3cfc4ec09657",
      "src": "https://github.com/hrsh7th/cmp-buffer"
    },
    "cmp-cmdline": {
      "rev": "d126061b624e0af6c3a556428712dd4d4194ec6d",
      "src": "https://github.com/hrsh7th/cmp-cmdline"
    },
    "cmp-nvim-lsp": {
      "rev": "cbc7b02bb99fae35cb42f514762b89b5126651ef",
      "src": "https://github.com/hrsh7th/cmp-nvim-lsp"
    },
    "cmp-path": {
      "rev": "c642487086dbd9a93160e1679a1327be111cbc25",
      "src": "https://github.com/hrsh7th/cmp-path"
    },
    "diffview.nvim": {
      "rev": "4516612fe98ff56ae0415a259ff6361a89419b0a",
      "src": "https://github.com/sindrets/diffview.nvim"
    },
    "dracula.nvim": {
      "rev": "ae752c13e95fb7c5f58da4b5123cb804ea7568ee",
      "src": "https://github.com/Mofiqul/dracula.nvim"
    },
    "gitsigns.nvim": {
      "rev": "72acb69020c92d99cf388bfeb390481ccec50c04",
      "src": "https://github.com/lewis6991/gitsigns.nvim"
    },
    "lualine.nvim": {
      "rev": "47f91c416daef12db467145e16bed5bbfe00add8",
      "src": "https://github.com/nvim-lualine/lualine.nvim"
    },
    "neo-tree.nvim": {
      "rev": "6ba0ef540a8dc92f9533433a3f10d414014676aa",
      "src": "https://github.com/nvim-neo-tree/neo-tree.nvim",
      "version": "3.0.0 - 4.0.0"
    },
    "neovim-session-manager": {
      "rev": "3409dc920d40bec4c901c0a122a80bee03d6d1e1",
      "src": "https://github.com/Shatur/neovim-session-manager"
    },
    "nui.nvim": {
      "rev": "de740991c12411b663994b2860f1a4fd0937c130",
      "src": "https://github.com/MunifTanjim/nui.nvim"
    },
    "nvim": {
      "rev": "4420f0a50dfde7ee79acf91ded8f97e02883a22a",
      "src": "https://github.com/catppuccin/nvim"
    },
    "nvim-autopairs": {
      "rev": "c2a0dd0d931d0fb07665e1fedb1ea688da3b80b4",
      "src": "https://github.com/windwp/nvim-autopairs"
    },
    "nvim-cmp": {
      "rev": "85bbfad83f804f11688d1ab9486b459e699292d6",
      "src": "https://github.com/hrsh7th/nvim-cmp"
    },
    "nvim-lspconfig": {
      "rev": "0b38bc74487e73489624d61396af7805af9cc75f",
      "src": "https://github.com/neovim/nvim-lspconfig"
    },
    "nvim-peekup": {
      "rev": "82251c54cd60f8504dfd9acd853eae57fe832447",
      "src": "https://github.com/gennaro-tedesco/nvim-peekup"
    },
    "nvim-web-devicons": {
      "rev": "6788013bb9cb784e606ada44206b0e755e4323d7",
      "src": "https://github.com/nvim-tree/nvim-web-devicons"
    },
    "plenary.nvim": {
      "rev": "b9fd5226c2f76c951fc8ed5923d85e4de065e509",
      "src": "https://github.com/nvim-lua/plenary.nvim"
    },
    "registers.nvim": {
      "rev": "c217f8f369e0886776cda6c94eab839b30a8940d",
      "src": "https://github.com/tversteeg/registers.nvim"
    },
    "telescope-ui-select.nvim": {
      "rev": "6e51d7da30bd139a6950adf2a47fda6df9fa06d2",
      "src": "https://github.com/nvim-telescope/telescope-ui-select.nvim"
    },
    "telescope.nvim": {
      "rev": "3333a52ff548ba0a68af6d8da1e54f9cd96e9179",
      "src": "https://github.com/nvim-telescope/telescope.nvim"
    },
    "vim": {
      "rev": "d4b0823100c702af127cba8dd5595a8f599041ec",
      "src": "https://github.com/dracula/vim"
    }
  }
}